openj/__init__.py
openj/db.py
openj/kanban.py
openj/schema.sql
openj/api/card.py
openj/api/lane.py
openj/api/user.py
openj/static/material-symbols-outlined.ttf
openj/static/material-symbols-outlined.woff2
openj/static/site.css
openj/templates/base.htm
openj/templates/create_card.html
openj/templates/create_user.html
openj/templates/kanban.html
openj/templates/update_card.html
openj/templates/update_user.html
openj-0.3.0.dist-info/LICENSE
openj-0.3.0.dist-info/METADATA
openj-0.3.0.dist-info/WHEEL
openj-0.3.0.dist-info/top_level.txt
openj-0.3.0.dist-info/RECORD
