Metadata-Version: 2.1
Name: openj
Version: 0.3.0
Summary: Kanban for Lean manufacturing.
Author-email: Michael Czigler <michaelczigler@icloud.com>
License: BSD 3-Clause License
Project-URL: repository, https://github.com/mcpcpc/openj
Keywords: kanban,lean,flask
Requires-Python: >=3.11
License-File: LICENSE
Requires-Dist: flask >=3.0.0
Provides-Extra: dev
Requires-Dist: coverage ; extra == 'dev'
Requires-Dist: black ; extra == 'dev'
Provides-Extra: prod
Requires-Dist: waitress ; extra == 'prod'
